{
  "books": [
    {
      "title": "con ca vang",
      "description": "tam giet chet cam va cam hoi sinh thanh cay thi",
      "id": "cU8B5Ex25"
    }
  ],
  "users": [
    {
      "name": "Linh",
      "id": "btg8PvTX8",
      "email": "tronglinh0611@gmail.com",
      "pass": "202cb962ac59075b964b07152d234b70",
      "isAdmin": true
    },
    {
      "name": "Tuyen",
      "email": "tuyen@gmail.com",
      "pass": "202cb962ac59075b964b07152d234b70",
      "id": "aDyyoMiYI",
      "isAdmin": false
    },
    {
      "name": "Duc",
      "email": "duc@gmail.com",
      "pass": "202cb962ac59075b964b07152d234b70",
      "id": "NzK9GVlro",
      "isAdmin": false
    }
  ],
  "transaction": [
    {
      "idBook": "cU8B5Ex25",
      "idUser": "btg8PvTX8",
      "iscomplete": false,
      "id": "OsIwZ47DS"
    }
  ]
}